pyropy/__init__.py
pyropy/firebehaviour.py
pyropy/helpers.py
pyropy/spreadmodels.py
pyropy/weatherdata.py
PyroPy-1.0.3a3.dist-info/LICENSE
PyroPy-1.0.3a3.dist-info/METADATA
PyroPy-1.0.3a3.dist-info/WHEEL
PyroPy-1.0.3a3.dist-info/top_level.txt
PyroPy-1.0.3a3.dist-info/RECORD
