Metadata-Version: 2.1
Name: PyroPy
Version: 1.0.3a3
Summary: Analysis of fire spread and intensity
Home-page: https://github.com/Geoffysicist/PyroPy
Author: Geoffysicist
Author-email: geoff.goldrick@rfs.nsw.gov.au
License: GPL-3.0-or-later
Project-URL: Documentation, https://geoffysicist.github.io/PyroPy/
Classifier: Development Status :: 3 - Alpha
Classifier: License :: OSI Approved :: GNU General Public License v3 or later (GPLv3+)
Classifier: Programming Language :: Python :: 3
Requires-Python: >=3.8
License-File: LICENSE
Requires-Dist: pandas
Requires-Dist: openpyxl
